wiredb/__init__.py
wiredb/channel.py
wiredb/client.py
wiredb/py.typed
wiredb/server.py
wiredb-0.7.1.dist-info/WHEEL
wiredb-0.7.1.dist-info/METADATA
wiredb-0.7.1.dist-info/RECORD
