Metadata-Version: 2.3
Name: wiredb
Version: 0.7.1
Summary: WireDB
Keywords: crdt
Author: David Brochart
Author-email: David Brochart <david.brochart@gmail.com>
License: The MIT License (MIT)
Classifier: Development Status :: 4 - Beta
Classifier: Intended Audience :: Developers
Classifier: License :: OSI Approved :: MIT License
Classifier: Programming Language :: Python
Classifier: Programming Language :: Python :: 3.10
Classifier: Programming Language :: Python :: 3.11
Classifier: Programming Language :: Python :: 3.12
Classifier: Programming Language :: Python :: 3.13
Classifier: Programming Language :: Python :: 3.14
Classifier: Programming Language :: Python :: Implementation :: CPython
Classifier: Programming Language :: Python :: Implementation :: PyPy
Requires-Dist: anyio>=4.11.0,<5.0.0
Requires-Dist: pycrdt>=0.12.41,<0.13.0
Requires-Dist: typing-extensions>=4.15.0,<5.0.0 ; python_full_version < '3.11'
Requires-Dist: wire-file>=0.7.1,<0.8.0 ; extra == 'file'
Requires-Dist: wire-memory>=0.7.1,<0.8.0 ; extra == 'memory'
Requires-Dist: wire-pipe>=0.7.1,<0.8.0 ; extra == 'pipe'
Requires-Dist: wire-websocket>=0.7.1,<0.8.0 ; extra == 'websocket'
Requires-Python: >=3.10
Project-URL: Homepage, https://github.com/davidbrochart/wiredb
Provides-Extra: file
Provides-Extra: memory
Provides-Extra: pipe
Provides-Extra: websocket
